{
  "1": {
    "videoId": "bHDkDeiEAQM",
    "title": "Mexico vs. South Africa Full Highlights | FIFA World Cup 2026",
    "thumbnail": "https://i.ytimg.com/vi/bHDkDeiEAQM/hqdefault.jpg",
    "channelTitle": "TSN",
    "status": "found",
    "fetchedAt": "2026-06-16T22:35:26.133Z",
    "lastAttemptAt": "2026-06-16T22:35:26.133Z",
    "attempts": 1,
    "searchQuery": "[TSN] Mexico vs. South Africa Full Highlights | FIFA World Cup 2026"
  },
  "2": {
    "videoId": "96DetiGHCiY",
    "title": "Korea Republic vs. Czechia Full Highlights | FIFA World Cup 2026",
    "thumbnail": "https://i.ytimg.com/vi/96DetiGHCiY/hqdefault.jpg",
    "channelTitle": "TSN",
    "status": "found",
    "fetchedAt": "2026-06-16T22:35:26.133Z",
    "lastAttemptAt": "2026-06-16T22:35:26.133Z",
    "attempts": 1,
    "searchQuery": "[TSN] South Korea vs. Czechia Full Highlights | FIFA World Cup 2026"
  },
  "3": {
    "videoId": "LLdJMgc9MYg",
    "title": "Canada vs. Bosnia and Herzegovina Full Highlights | FIFA World Cup 2026",
    "thumbnail": "https://i.ytimg.com/vi/LLdJMgc9MYg/hqdefault.jpg",
    "channelTitle": "TSN",
    "status": "found",
    "fetchedAt": "2026-06-16T22:35:26.133Z",
    "lastAttemptAt": "2026-06-16T22:35:26.133Z",
    "attempts": 1,
    "searchQuery": "[TSN] Canada vs. Bosnia Full Highlights | FIFA World Cup 2026"
  },
  "4": {
    "videoId": "Jbn751Fip44",
    "title": "USA vs. Paraguay Full Highlights | FIFA World Cup 2026",
    "thumbnail": "https://i.ytimg.com/vi/Jbn751Fip44/hqdefault.jpg",
    "channelTitle": "TSN",
    "status": "found",
    "fetchedAt": "2026-06-16T22:35:26.133Z",
    "lastAttemptAt": "2026-06-16T22:35:26.133Z",
    "attempts": 1,
    "searchQuery": "[TSN] USA vs. Paraguay Full Highlights | FIFA World Cup 2026"
  },
  "5": {
    "videoId": "Z-9EIWllZNM",
    "title": "Qatar vs. Switzerland Full Highlights | FIFA World Cup 2026",
    "thumbnail": "https://i.ytimg.com/vi/Z-9EIWllZNM/hqdefault.jpg",
    "channelTitle": "TSN",
    "status": "found",
    "fetchedAt": "2026-06-16T22:35:26.133Z",
    "lastAttemptAt": "2026-06-16T22:35:26.133Z",
    "attempts": 1,
    "searchQuery": "[TSN] Qatar vs. Switzerland Full Highlights | FIFA World Cup 2026"
  },
  "6": {
    "videoId": "sW44G8KxAbw",
    "title": "Brazil vs. Morocco Full Highlights | FIFA World Cup 2026",
    "thumbnail": "https://i.ytimg.com/vi/sW44G8KxAbw/hqdefault.jpg",
    "channelTitle": "TSN",
    "status": "found",
    "fetchedAt": "2026-06-16T22:35:26.133Z",
    "lastAttemptAt": "2026-06-16T22:35:26.133Z",
    "attempts": 1,
    "searchQuery": "[TSN] Brazil vs. Morocco Full Highlights | FIFA World Cup 2026"
  },
  "7": {
    "videoId": "FXn3ZwNIiHQ",
    "title": "Haiti vs. Scotland Full Highlights | FIFA World Cup 2026",
    "thumbnail": "https://i.ytimg.com/vi/FXn3ZwNIiHQ/hqdefault.jpg",
    "channelTitle": "TSN",
    "status": "found",
    "fetchedAt": "2026-06-16T22:35:26.133Z",
    "lastAttemptAt": "2026-06-16T22:35:26.133Z",
    "attempts": 1,
    "searchQuery": "[TSN] Haiti vs. Scotland Full Highlights | FIFA World Cup 2026"
  },
  "8": {
    "videoId": "w2aYzT0iTsQ",
    "title": "Australia vs. Türkiye Full Highlights | FIFA World Cup 2026",
    "thumbnail": "https://i.ytimg.com/vi/w2aYzT0iTsQ/hqdefault.jpg",
    "channelTitle": "TSN",
    "status": "found",
    "fetchedAt": "2026-06-16T22:35:26.133Z",
    "lastAttemptAt": "2026-06-16T22:35:26.133Z",
    "attempts": 1,
    "searchQuery": "[TSN] Australia vs. Turkey Full Highlights | FIFA World Cup 2026"
  },
  "9": {
    "videoId": "AFiS2yJeZqo",
    "title": "Germany vs. Curacao Full Highlights | FIFA World Cup 2026",
    "thumbnail": "https://i.ytimg.com/vi/AFiS2yJeZqo/hqdefault.jpg",
    "channelTitle": "TSN",
    "status": "found",
    "fetchedAt": "2026-06-16T22:35:26.133Z",
    "lastAttemptAt": "2026-06-16T22:35:26.133Z",
    "attempts": 1,
    "searchQuery": "[TSN] Germany vs. Curaçao Full Highlights | FIFA World Cup 2026"
  },
  "10": {
    "videoId": "Lq43D52MfkY",
    "title": "Netherlands vs. Japan Full Highlights | FIFA World Cup 2026",
    "thumbnail": "https://i.ytimg.com/vi/Lq43D52MfkY/hqdefault.jpg",
    "channelTitle": "TSN",
    "status": "found",
    "fetchedAt": "2026-06-16T22:35:26.133Z",
    "lastAttemptAt": "2026-06-16T22:35:26.133Z",
    "attempts": 1,
    "searchQuery": "[TSN] Netherlands vs. Japan Full Highlights | FIFA World Cup 2026"
  },
  "11": {
    "videoId": "mKoy6MVdcAk",
    "title": "Ivory Coast vs. Ecuador Full Highlights | FIFA World Cup 2026",
    "thumbnail": "https://i.ytimg.com/vi/mKoy6MVdcAk/hqdefault.jpg",
    "channelTitle": "TSN",
    "status": "found",
    "fetchedAt": "2026-06-16T22:35:26.133Z",
    "lastAttemptAt": "2026-06-16T22:35:26.133Z",
    "attempts": 1,
    "searchQuery": "[TSN] Cote d'Ivoire vs. Ecuador Full Highlights | FIFA World Cup 2026"
  },
  "12": {
    "videoId": "YUD8Fq3gLWE",
    "title": "Spain vs. Cabo Verde Full Highlights | FIFA World Cup 2026",
    "thumbnail": "https://i.ytimg.com/vi/YUD8Fq3gLWE/hqdefault.jpg",
    "channelTitle": "TSN",
    "status": "found",
    "fetchedAt": "2026-06-16T22:35:26.133Z",
    "lastAttemptAt": "2026-06-16T22:35:26.133Z",
    "attempts": 1,
    "searchQuery": "[TSN] Spain vs. Cabo Verde Full Highlights | FIFA World Cup 2026"
  },
  "13": {
    "videoId": "TC9tqtH0CkA",
    "title": "Sweden vs. Tunisia Full Highlights | FIFA World Cup 2026",
    "thumbnail": "https://i.ytimg.com/vi/TC9tqtH0CkA/hqdefault.jpg",
    "channelTitle": "TSN",
    "status": "found",
    "fetchedAt": "2026-06-16T22:35:26.133Z",
    "lastAttemptAt": "2026-06-16T22:35:26.133Z",
    "attempts": 1,
    "searchQuery": "[TSN] Sweden vs. Tunisia Full Highlights | FIFA World Cup 2026"
  },
  "14": {
    "videoId": "Tz9R1OYdTSs",
    "title": "Saudi Arabia vs Uruguay Extended Highlights 🌎🏆 2026 FIFA World Cup™",
    "thumbnail": "https://i.ytimg.com/vi/Tz9R1OYdTSs/hqdefault.jpg",
    "channelTitle": "FOX Sports",
    "status": "found",
    "fetchedAt": "2026-06-17T06:09:16.714Z",
    "lastAttemptAt": "2026-06-17T06:09:16.714Z",
    "attempts": 1,
    "searchQuery": "[global] Saudi Arabia vs. Uruguay Full Highlights | FIFA World Cup 2026"
  },
  "17": {
    "videoId": "WxOfHAy6obs",
    "title": "FRANCE DOMINATE! France 3-1 Senegal | Full Match Highlights | FIFA World Cup 2026",
    "thumbnail": "https://i.ytimg.com/vi/WxOfHAy6obs/hqdefault.jpg",
    "channelTitle": "moneycontrol",
    "status": "found",
    "fetchedAt": "2026-06-17T06:09:16.714Z",
    "lastAttemptAt": "2026-06-17T06:09:16.714Z",
    "attempts": 1,
    "searchQuery": "[global] France vs. Senegal Full Highlights | FIFA World Cup 2026"
  },
  "18": {
    "videoId": "ku1hsMdKDXQ",
    "title": "Iraq vs Norway Extended Highlights 🌎🏆2026 FIFA World Cup™",
    "thumbnail": "https://i.ytimg.com/vi/ku1hsMdKDXQ/hqdefault.jpg",
    "channelTitle": "FOX Sports",
    "status": "found",
    "fetchedAt": "2026-06-17T06:09:16.714Z",
    "lastAttemptAt": "2026-06-17T06:09:16.714Z",
    "attempts": 1,
    "searchQuery": "[global] Iraq vs. Norway Full Highlights | FIFA World Cup 2026"
  },
  "40": {
    "videoId": "0IQd36iZGVs",
    "title": "Spain draws?! Late drama for Belgium, Uruguay &amp; Iran Matchday 5 🤯 2026 FIFA World Cup™ Best Moments",
    "thumbnail": "https://i.ytimg.com/vi/0IQd36iZGVs/hqdefault.jpg",
    "channelTitle": "FOX Sports",
    "status": "found",
    "fetchedAt": "2026-06-16T22:35:26.133Z",
    "lastAttemptAt": "2026-06-17T06:09:16.714Z",
    "attempts": 2,
    "searchQuery": "[global] Belgium vs. Iran Full Highlights | FIFA World Cup 2026"
  },
  "42": {
    "videoId": "UZ_7qFbFYRY",
    "title": "Iran vs New Zealand Extended Highlights 🌎🏆 2026 FIFA World Cup™",
    "thumbnail": "https://i.ytimg.com/vi/UZ_7qFbFYRY/hqdefault.jpg",
    "channelTitle": "FOX Sports",
    "status": "found",
    "fetchedAt": "2026-06-17T06:09:16.714Z",
    "lastAttemptAt": "2026-06-17T06:09:16.714Z",
    "attempts": 1,
    "searchQuery": "[global] Egypt vs. New Zealand Full Highlights | FIFA World Cup 2026"
  },
  "_meta": {
    "updatedAt": "2026-06-17T06:09:16.714Z",
    "totalFound": 18,
    "totalPending": 0,
    "quotaUsed": 1001
  }
}
